{"name":"APIMASH Starter Kits for Windows","tagline":"The APIMASH Starter Kits for Windows demonstrate how to use public Web Service API's such as Edmunds, Tom-Tom, Twitter, Tumblr, Yelp, Meetup and many others.","body":"# Your App Starts Here\r\n\r\n***\r\n\r\nThe APIMASH Starter Kits for Windows demonstrate how to use public Web Service API's such as Edmunds, Tom-Tom, Twitter, Tumblr, Yelp, Meetup and many others. These Starter Kits will put you on the fast path to publishing your first Windows 8 App using these rich datasets.\r\n\r\n# App Builder\r\nWith unprecedented reach across a range of devices and availability in over 200 markets, there's never been a better time to build for Windows and Windows Phone. From start to finish, [App Builder](http://build.windowsstore.com/) provides the tools and support you need to ensure your great idea is available to millions.","google":"","note":"Don't delete this file! It's used internally to help with page regeneration."}